ppt.py
mcp_chatppt-1.0.1.dist-info/METADATA
mcp_chatppt-1.0.1.dist-info/WHEEL
mcp_chatppt-1.0.1.dist-info/top_level.txt
mcp_chatppt-1.0.1.dist-info/RECORD
