Metadata-Version: 2.4
Name: mcp-chatppt
Version: 1.0.1
Summary: Add your description here
Requires-Python: >=3.13
